{"selected":[{"y":2002,"t":"德國、法國、義大利、荷蘭等12個歐洲聯盟成員國組成的歐元區正式啟用歐元（圖）。"},{"y":1959,"t":"菲德尔·卡斯特罗領導的革命軍控制古巴首都哈瓦那，富尔亨西奥·巴蒂斯塔政權垮臺。"},{"y":1901,"t":"英國在澳大利亚的六個海外殖民地合併成立澳大利亚聯邦，埃德蒙·巴頓成為首任總理。"},{"y":1801,"t":"大不列顛王國和愛爾蘭王國根據《聯合法令》建立大不列顛暨愛爾蘭聯合王國。"},{"y":-45,"t":"羅馬共和國獨裁官尤利乌斯·凯撒規定開始使用儒略曆，取代舊有的羅馬曆。"}],"events":[{"y":2026,"t":"瑞士瓦萊州一家酒吧發生爆炸並引發火災，造成至少47人死亡、115人受傷。"},{"y":2024,"t":"臺灣鐵路管理局改制為臺灣鐵路公司。"},{"y":2024,"t":"《中華人民共和國愛國主義教育法》正式實施，條文列出的適用對象包括「港澳台同胞」和海外僑胞，愛國主義教育的主要內容包括「習近平新時代中國特色社會主義思想」。"},{"y":2024,"t":"日本石川縣能登半島發生Mj 7.6地震，造成236人死亡、1,279人受傷。"},{"y":2024,"t":"出現在1928年動畫片《汽船威利號》中的第一版米老鼠形象進入公有領域。"},{"y":2023,"t":"克羅埃西亞正式啟用歐元，並加入申根區。"},{"y":2022,"t":"由15個國家簽署的區域全面經濟夥伴協定正式生效，成為世界上規模最大的自由貿易協定。"},{"y":2022,"t":"迪士尼頻道退出台灣。"},{"y":2019,"t":"中華民國實施大型餐飲業如連鎖速食店等，內用將禁止提供塑膠吸管的規定；"},{"y":2019,"t":"中華民國依法屆期終止第三代行動通訊（3G）業務。"},{"y":2019,"t":"美國國家航空暨太空總署的新視野號飛越小行星「終極遠境」，是人類探測距離最遠的天體。"},{"y":2017,"t":"枪手袭击土耳其伊斯坦布尔的夜总会。至少有39人死亡，而袭击者的动机尚不清楚。"},{"y":2017,"t":"聯合國第9任秘书长──葡萄牙籍安東尼歐·古特瑞斯上任。"},{"y":2015,"t":"立陶宛成為第19個加入歐元區的國家。"},{"y":2014,"t":"拉脫維亞成為第18個加入歐元區的國家。"},{"y":2014,"t":"歐洲聯盟解除羅馬尼亞與保加利亞兩國公民工作限制，該兩國公民可在歐盟全境自由工作。"},{"y":2013,"t":"象牙海岸阿必尚烏弗埃-博瓦尼球場（英语：Stade Félix Houphouët-Boigny）發生人踩人慘劇，造成61人死亡，超過200人受傷。"},{"y":2010,"t":"世界上最大的自由贸易区中国―东盟自由贸易区正式建成。"},{"y":2010,"t":"巴基斯坦西北边境省一处村庄内的排球场遭到自杀式汽车炸弹袭击，造成至少95人死亡，100多人受伤。"},{"y":2010,"t":"美国新罕布什尔州成为全美第五个将同性婚姻合法化的州份。"},{"y":2009,"t":"挪威成为世界上第六个承认同性婚姻的国家。"},{"y":2009,"t":"梵蒂冈宣称“意大利的法律过于繁杂，而且欠缺稳定、时常和天主教教义相违背”，正式废除《拉特兰协议》，不再自动采纳意大利议会通过的法律。"},{"y":2009,"t":"斯洛伐克成为欧元区第十六个成员国。"},{"y":2009,"t":"曼谷Santika夜总会发生火灾，造成66人死亡。"},{"y":2007,"t":"羅馬尼亞和保加利亞加入歐盟。斯洛文尼亞加入歐元區。"},{"y":2007,"t":"印尼亞當航空574號班機於蘇拉威西島墜毀，102人全部罹難。"},{"y":2007,"t":"曼谷連環爆炸案發生。"},{"y":2007,"t":"聯合國第8任秘书长──韓國籍潘基文上任。"},{"y":2007,"t":"中華人民共和國死刑案件統一收回最高人民法院行使。"},{"y":2006,"t":"香港警察訓練學校升格成為香港警察學院。"}],"births":[{"y":2001,"t":"蔣依依，中國女演員"},{"y":2001,"t":"Winter，韓國女子偶像團體aespa成員"},{"y":2000,"t":"孫健豪，臺灣網路名人"},{"y":2000,"t":"卡莉娜·梁，加拿大女演員"},{"y":1999,"t":"趙磊，中國男子偶像團體X玖少年團、R1SE成員"},{"y":1997,"t":"阿布德拉汗·哈魯恩，卡達田徑運動員（2021年逝世）"},{"y":1997,"t":"楊俊瀚，臺灣男子田徑運動員"},{"y":1997,"t":"阿卜杜拉汗·阿巴卡爾·穆罕默德，沙烏地阿拉伯男子田徑運動員"},{"y":1996,"t":"林立，臺灣職業棒球運動員"},{"y":1996,"t":"錢錕，韓國男子偶像團體NCT成員"},{"y":1995,"t":"萨达尔·阿兹蒙，伊朗足球运动員"},{"y":1995,"t":"權聖晙，韓國廚師"},{"y":1994,"t":"黃思恬，新加坡女演員"},{"y":1993,"t":"鄭美美，韓國女子偶像團體gugudan成員"},{"y":1993,"t":"西凡·哈桑，荷蘭女子田徑運動員"}],"deaths":[{"y":2026,"t":"黃東璧，中國外交官（1939年出生）"},{"y":2026,"t":"內扎特·達奇，科索沃政治人物，前任科索沃總統（1944年出生）"},{"y":2026,"t":"袁祥仁，香港導演、武術指導、武打演員（1957年出生）"},{"y":2024,"t":"巴斯德奧·潘戴，千里達及托巴哥律師、政治人物，第5任千里達及托巴哥總理（1933年出生）"},{"y":2024,"t":"Lynja，美國TikToker、廚師（1956年出生）"},{"y":2024,"t":"張誌家，台灣旅日棒球選手（1980年出生）"},{"y":2023,"t":"韓銳，中國藥理學家（1930年出生）"},{"y":2023,"t":"侯一民，中國油畫家、雕塑家、美術教育家（1930年出生）"},{"y":2023,"t":"韋廉，中國電影導演（1945年出生）"},{"y":2023,"t":"維克托·伊萬年科，蘇聯和俄羅斯國家安全機構領導人（1947年出生）"},{"y":2021,"t":"埃爾米拉·米尼塔·戈登，貝里斯總督（1930年出生）"},{"y":2020,"t":"大衛·斯特恩，前任美國國家籃球協會總裁（1942年出生）"},{"y":2017,"t":"王家禧，香港漫画家，漫畫《老夫子》的作者（1924年出生）"},{"y":2015,"t":"马里奥·库默，美國政治人物（1932年出生）"},{"y":2013,"t":"帕蒂·佩奇，美國女歌手（1927年出生）"}]}