{"selected":[{"y":2011,"t":"受突尼西亞茉莉花革命的影響，部分中國異見者發起中國茉莉花革命。"},{"y":1936,"t":"东北抗日联军（圖）成立。"},{"y":1816,"t":"由義大利作曲家焦阿基諾·羅西尼創作的歌劇《塞維亞的理髮師》在羅馬首次演出。"},{"y":1547,"t":"在亨利八世逝世後，年僅9歲的愛德華六世在威斯敏斯特教堂加冕成為英格蘭國王。"},{"y":1472,"t":"在與丹麥的瑪格麗特結婚後，蘇格蘭國王詹姆斯三世獲得奧克尼和设德兰兩地。"}],"events":[{"y":2022,"t":"中國北京市國家體育場舉行2022年冬季奧林匹克運動會的閉幕式，其中挪威代表團贏得最多面金牌。"},{"y":2022,"t":"衣索比亞青尼羅河的衣索比亞復興大壩正式啟用發電，此為全非洲規模最大的水力發電工程。"},{"y":2022,"t":"尼泊爾聯邦議會正式批准與美國簽署的千禧年挑戰計劃協議，首都加德滿都爆發示威運動。"},{"y":2011,"t":"受突尼西亞茉莉花革命的影響，部分中國異見者發起中國茉莉花革命。"},{"y":2005,"t":"西班牙成為第一個針對欧盟宪法草案舉行公民投票的國家，投票結果以壓倒性的票數通過歐盟憲法草案。"},{"y":2002,"t":"埃及火車大火，370餘人死亡。"},{"y":1998,"t":"15歲的美國花式滑冰運動員塔拉·利平斯基成為當時冬季奧運史上最年輕的金牌得主。"},{"y":1992,"t":"英格蘭超級聯賽成立。"},{"y":1988,"t":"亞塞拜然的納戈爾諾－卡拉巴赫自治州決定與亞美尼亞統一，引發纳戈尔诺－卡拉巴赫战争。"},{"y":1986,"t":"英法簽定坎特伯雷條約（英语：Treaty of Canterbury），開挖英法海底隧道。"},{"y":1985,"t":"中华人民共和国首个南极考察站中国南极长城站举行落成典礼。"},{"y":1972,"t":"耗資三億二千萬港元興建的香港紅磡海底隧道舉行貫通儀式。"},{"y":1970,"t":"巴吞他尼府的法身寺開山，是泰國最大的佛教寺廟之一。"},{"y":1968,"t":"中国空间技术研究院成立。"},{"y":1965,"t":"美國國家航空暨太空總署的游騎兵8號太空船在任務最後23分鐘內傳回7,137張月球照片，隨後如計畫般墜入寧靜海。"},{"y":1962,"t":"美国宇航员约翰·葛伦乘坐水星-宇宙神6号升空，为首个进入地球轨道的美国太空人。"},{"y":1958,"t":"中國与阿尔及利亚建交。"},{"y":1947,"t":"中國人民解放軍在萊蕪戰役取得勝利。"},{"y":1943,"t":"墨西哥米却肯州一块玉米田里的裂缝喷发口开始涌出岩浆，最终形成帕里库廷火山。"},{"y":1943,"t":"《星期六晚郵報》刊載了諾曼·洛克威爾創作的《四大自由》系列首幅畫作，該系列堪稱史上傳播最廣的繪畫作品之一，旨在支持美國總統富蘭克林·德拉諾·羅斯福提出的四大自由理念。"},{"y":1936,"t":"东北抗日联军成立。"},{"y":1915,"t":"巴拿马运河开通。"},{"y":1911,"t":"中國东三省发生鼠疫。"},{"y":1897,"t":"大清邮政在北京开办。"},{"y":1872,"t":"位于美国纽约的大都会艺术博物馆首次开放，是世界上最大的艺术博物馆之一。"},{"y":1846,"t":"波蘭起義軍在克拉科夫自由市發動起義，試圖激發爭取民族獨立的鬥爭，但九天後遭奧地利帝國鎮壓。"},{"y":1816,"t":"由義大利作曲家焦阿基諾·羅西尼創作的歌劇《塞維亞的理髮師》在羅馬首次演出。"},{"y":1798,"t":"法國軍官路易-亞歷山大·貝爾蒂埃率領軍隊佔領羅馬，並將教宗庇護六世押解回西恩納。"},{"y":1685,"t":"羅貝爾·德·拉薩勒率領殖民者在馬塔戈爾達灣（英语：Matagorda Bay）附近登陸，並建立法屬德克薩斯。"},{"y":1547,"t":"在亨利八世逝世後，年僅9歲的愛德華六世在西敏寺加冕成為英格蘭國王。"}],"births":[{"y":2007,"t":"梁善知，香港女藝人"},{"y":2006,"t":"賀博，美國男子籃球運動員"},{"y":2003,"t":"奧莉維亞·羅德里戈，美國創作歌手、演員"},{"y":2000,"t":"米拉克·克里什托夫，匈牙利男子游泳運動員"},{"y":1998,"t":"彼得·帕夫拉克，波蘭鋼琴家"},{"y":1996,"t":"伊藤萬理華，日本偶像團體乃木坂46成員"},{"y":1994,"t":"布里吉德·科斯蓋，肯亞田徑運動員"},{"y":1993,"t":"橋本奈奈未，日本女子偶像團體乃木坂46成員"},{"y":1993,"t":"喬治雅·顧，英國女歌手、作詞家"},{"y":1993,"t":"莊·皮雷斯，烏拉圭職業足球運動員"},{"y":1992,"t":"雷·尼科爾森，美國演員"},{"y":1991,"t":"莎莉·魯尼，愛爾蘭作家"},{"y":1991,"t":"張庭瑚，台灣演員"},{"y":1991,"t":"海蒂·狄亞士，菲律賓舉重運動員"},{"y":1988,"t":"邱慧雯，台灣藝人"}],"deaths":[{"y":2026,"t":"李乙廷，臺灣政治人物（1954年出生）"},{"y":2025,"t":"大衛·L·博倫，美國政治人物（1941年出生）"},{"y":2025,"t":"漢斯·凱爾·拉斯穆森，丹麥男子射擊運動員（1954年出生）"},{"y":2024,"t":"山本陽子，日本女演員（1942年出生）"},{"y":2024,"t":"安德烈亞斯·布雷默，德國職業足球運動員（1960年出生）"},{"y":2023,"t":"謝苗·格施泰因，俄羅斯物理學家（1929年出生）"},{"y":2021,"t":"黃崑濱，記錄片《無米樂》的主角之一（1929年出生）"},{"y":2016,"t":"高菊花，臺灣女歌手、教師（1932年出生）"},{"y":2016,"t":"洪百慧，台灣台語女歌手（1977年出生）"},{"y":2014,"t":"路学长，中国著名导演（1964年出生）"},{"y":2012,"t":"黃崑巖，干擾素與感染免疫研究者，國立成功大學醫學院創院院長（1933年出生）"},{"y":2010,"t":"亚历山大·黑格，美國政治人物，第59任美國國務卿（1924年出生）"},{"y":2009,"t":"傅禎彝，中華民國空軍第一批儲訓女飛行員（1921年出生）"},{"y":2006,"t":"方召麐，傑出國畫大師，香港特區前政務司司長陳方安生的母親（1914年出生）"},{"y":2000,"t":"郭啟彰，臺灣水產養殖者（1912年出生）"}]}